<?xml version="1.0"?>
<scpd xmlns="urn:schemas-upnp-org:service-1-0">
  <specVersion>
    <major>1</major>
    <minor>0</minor>
  </specVersion>

  <actionList>
    <action>
      <name>Play</name>
      <argumentList>
        <argument>
          <name>Value</name>
          <direction>in</direction>
          <relatedStateVariable>TransportState</relatedStateVariable>
        </argument>
      </argumentList>
    </action>

    <action>
      <name>Pause</name>
    </action>

    <action>
      <name>Stop</name>
    </action>

    <action>
      <name>Next</name>
    </action>

    <action>
      <name>Previous</name>
    </action>

    <action>
      <name>Insert</name>
      <argumentList>
        <argument>
          <name>AfterId</name>
          <direction>in</direction>
          <relatedStateVariable>TrackId</relatedStateVariable>
        </argument>
        <argument>
          <name>Uri</name>
          <direction>in</direction>
          <relatedStateVariable>Uri</relatedStateVariable>
        </argument>
        <argument>
          <name>Metadata</name>
          <direction>in</direction>
          <relatedStateVariable>Metadata</relatedStateVariable>
        </argument>
        <argument>
          <name>NewId</name>
          <direction>out</direction>
          <relatedStateVariable>TrackId</relatedStateVariable>
        </argument>
      </argumentList>
    </action>
  </actionList>

  <serviceStateTable>
    <stateVariable sendEvents="yes">
      <name>TransportState</name>
      <dataType>string</dataType>
      <allowedValueList>
        <allowedValue>Playing</allowedValue>
        <allowedValue>Paused</allowedValue>
        <allowedValue>Stopped</allowedValue>
      </allowedValueList>
    </stateVariable>

    <stateVariable sendEvents="no">
      <name>Uri</name>
      <dataType>string</dataType>
    </stateVariable>

    <stateVariable sendEvents="no">
      <name>Metadata</name>
      <dataType>string</dataType>
    </stateVariable>

    <stateVariable sendEvents="no">
      <name>TrackId</name>
      <dataType>ui4</dataType>
    </stateVariable>
  </serviceStateTable>
</scpd>
